chutes/__init__.py
chutes/_version.py
chutes/cfsv
chutes/cfsv_wrapper.py
chutes/chutes-inspecto.so
chutes/chutes-logintercept.so
chutes/chutes-netnanny.so
chutes/cli.py
chutes/config.py
chutes/constants.py
chutes/crud.py
chutes/exception.py
chutes/inspecto.py
chutes/metrics.py
chutes/chute/__init__.py
chutes/chute/base.py
chutes/chute/cord.py
chutes/chute/job.py
chutes/chute/node_selector.py
chutes/chute/template/__init__.py
chutes/chute/template/diffusion.py
chutes/chute/template/embedding.py
chutes/chute/template/helpers.py
chutes/chute/template/sglang.py
chutes/chute/template/vllm.py
chutes/entrypoint/__init__.py
chutes/entrypoint/_shared.py
chutes/entrypoint/api_key.py
chutes/entrypoint/build.py
chutes/entrypoint/deploy.py
chutes/entrypoint/fingerprint.py
chutes/entrypoint/logger.py
chutes/entrypoint/register.py
chutes/entrypoint/report.py
chutes/entrypoint/run.py
chutes/entrypoint/secret.py
chutes/entrypoint/share.py
chutes/entrypoint/ssh.py
chutes/entrypoint/verify.py
chutes/entrypoint/warmup.py
chutes/envcheck/__init__.py
chutes/envcheck/core.py
chutes/envdump/__init__.py
chutes/envdump/envdump.so
chutes/image/__init__.py
chutes/image/directive/__init__.py
chutes/image/directive/add.py
chutes/image/directive/apt.py
chutes/image/directive/base_image.py
chutes/image/directive/entrypoint.py
chutes/image/directive/env.py
chutes/image/directive/generic_run.py
chutes/image/directive/maintainer.py
chutes/image/directive/user.py
chutes/image/directive/workdir.py
chutes/image/standard/__init__.py
chutes/image/standard/diffusion.py
chutes/image/standard/sglang.py
chutes/image/standard/vllm.py
chutes/pyarmor_runtime_006563/__init__.py
chutes/pyarmor_runtime_006563/py310/pyarmor_runtime.so
chutes/pyarmor_runtime_006563/py311/pyarmor_runtime.so
chutes/pyarmor_runtime_006563/py312/pyarmor_runtime.so
chutes/pyarmor_runtime_006563/py313/pyarmor_runtime.so
chutes/util/__init__.py
chutes/util/auth.py
chutes/util/context.py
chutes/util/schema.py
chutes/util/user.py
chutes-0.4.2.dist-info/LICENSE
chutes-0.4.2.dist-info/METADATA
chutes-0.4.2.dist-info/WHEEL
chutes-0.4.2.dist-info/entry_points.txt
chutes-0.4.2.dist-info/top_level.txt
chutes-0.4.2.dist-info/RECORD
