Metadata-Version: 2.1
Name: chutes
Version: 0.4.2
Summary: Chutes development kit and CLI.
Home-page: https://github.com/rayonlabs/chutes
Author: Jon Durbin
Classifier: Development Status :: 3 - Alpha
Classifier: Intended Audience :: Developers
Classifier: Operating System :: POSIX :: Linux
Classifier: Programming Language :: Python :: 3.10
License-File: LICENSE
Requires-Dist: aiohttp[speedups]<4,>=3.10
Requires-Dist: backoff<3,>=2.2
Requires-Dist: requests>=2.32
Requires-Dist: loguru==0.7.2
Requires-Dist: fastapi>=0.110
Requires-Dist: uvicorn<0.38,>=0.32.0
Requires-Dist: pydantic<3,>=2.9
Requires-Dist: orjson>=3.10
Requires-Dist: fickling==0.1.3
Requires-Dist: setuptools>=0.75
Requires-Dist: substrate-interface>=1.7.11
Requires-Dist: rich>=13.0.0
Requires-Dist: typer>=0.12.5
Requires-Dist: graval==0.2.6
Requires-Dist: prometheus-client==0.21.0
Requires-Dist: cryptography
Requires-Dist: psutil
Requires-Dist: pyjwt>=2.10.1
Requires-Dist: netifaces
Requires-Dist: pyudev
Requires-Dist: aiofiles>=23
Requires-Dist: semver
Requires-Dist: huggingface-hub
Provides-Extra: dev
Requires-Dist: black; extra == "dev"
Requires-Dist: flake8; extra == "dev"
Requires-Dist: wheel; extra == "dev"
Requires-Dist: pytest; extra == "dev"
